[
    {
        "name": "Wooden Chair",
        "description": "Ergonomic wooden chair",
        "price": 45.99,
        "quantity": 10,
        "categoryId": "9d041e13-d69c-4672-8f1e-52b530bd9261",
        "locationId": "1335fc07-ba7d-4b72-9576-e0fec9ae11b2"
    },
    {
        "name": "Cement Bag",
        "description": "50kg Portland cement",
        "price": 8.50,
        "quantity": 50,
        "categoryId": "e9464375-e857-4c89-817f-7d08724e089b",
        "locationId": "d24c1aa7-d985-4fe3-abc8-32df6cbbb2bd"
    },
    {
        "name": "Hammer",
        "description": "Steel claw hammer",
        "price": 12.00,
        "quantity": 30,
        "categoryId": "e082f3d6-d962-41ab-b149-48275cdb3880",
        "locationId": "4e730b83-9de1-4bca-970f-9224c534665f"
    },
    {
        "name": "Maize Seeds",
        "description": "Hybrid maize seeds pack",
        "price": 5.75,
        "quantity": 100,
        "categoryId": "7fb56f34-1ce5-4317-b9eb-960248f70f51",
        "locationId": "6599e2f7-dd2a-413a-857d-07b90e10e453"
    },
    {
        "name": "Smartphone",
        "description": "Latest model smartphone",
        "price": 299.99,
        "quantity": 20,
        "categoryId": "61f24ef2-61f3-4152-9a30-910f7057f713",
        "locationId": "28b71b99-c655-48c9-8faf-69ca15bcd3f2"
    },
    {
        "name": "T-Shirt",
        "description": "Cotton unisex T-shirt",
        "price": 9.99,
        "quantity": 200,
        "categoryId": "ae42db6a-4f4b-49a5-9ef1-3551141f6e59",
        "locationId": "5f84c115-cf12-4954-947b-c9672b6ebb61"
    },
    {
        "name": "Car Battery",
        "description": "12V maintenance-free battery",
        "price": 85.00,
        "quantity": 15,
        "categoryId": "bc058798-d669-458b-8945-98bbe0ae4c4a",
        "locationId": "d104cc60-3867-4fc5-83f8-368fdcdb1684"
    },
    {
        "name": "Novel Book",
        "description": "Bestselling fiction novel",
        "price": 14.50,
        "quantity": 40,
        "categoryId": "2f70d404-8b93-461e-973d-b04152bf62aa",
        "locationId": "8e45a5da-fe9e-462f-8648-017348d7ca51"
    },
    {
        "name": "Vitamin C",
        "description": "1000mg Vitamin C tablets",
        "price": 7.25,
        "quantity": 60,
        "categoryId": "b4a51cd7-1bf5-4607-ac70-bf97089d6f9c",
        "locationId": "072a99e9-0806-4af7-a838-240dc173fba7"
    },
    {
        "name": "Football",
        "description": "Standard size football",
        "price": 19.99,
        "quantity": 25,
        "categoryId": "ffa4f091-f6a2-4782-9b5c-593538e01e22",
        "locationId": "eb2dc01c-43d2-4d08-9bd7-5f05b9a2221f"
    },
    {
        "name": "Dining Table",
        "description": "6-seater wooden dining table",
        "price": 120.00,
        "quantity": 5,
        "categoryId": "9d041e13-d69c-4672-8f1e-52b530bd9261",
        "locationId": "8b74512a-d24b-447e-8ba0-e370a4e794d4"
    },
    {
        "name": "Bricks Pack",
        "description": "Pack of 100 clay bricks",
        "price": 30.00,
        "quantity": 20,
        "categoryId": "e9464375-e857-4c89-817f-7d08724e089b",
        "locationId": "4bb4b78a-0773-412b-86c7-6733bb5bced9"
    },
    {
        "name": "Saw",
        "description": "Handheld wood saw",
        "price": 15.00,
        "quantity": 35,
        "categoryId": "10aa005f-e047-4ccf-95bf-e959ec7c312d",
        "locationId": "87fb1d08-3395-4c58-816d-f1d78534a7db"
    },
    {
        "name": "Fertilizer",
        "description": "Organic compost fertilizer",
        "price": 10.00,
        "quantity": 80,
        "categoryId": "7fb56f34-1ce5-4317-b9eb-960248f70f51",
        "locationId": "284baa19-4162-461e-a234-c00ec4c6ec47"
    },
    {
        "name": "Laptop",
        "description": "15-inch laptop with SSD",
        "price": 750.00,
        "quantity": 10,
        "categoryId": "61f24ef2-61f3-4152-9a30-910f7057f713",
        "locationId": "035fdccf-1879-4fb0-9a64-9bf76e988b4f"
    },
    {
        "name": "Jeans",
        "description": "Denim jeans for men",
        "price": 25.00,
        "quantity": 60,
        "categoryId": "ae42db6a-4f4b-49a5-9ef1-3551141f6e59",
        "locationId": "5bfb5c0f-4796-4e17-8a76-dbfdbdc5ff0f"
    },
    {
        "name": "Engine Oil",
        "description": "5L synthetic engine oil",
        "price": 40.00,
        "quantity": 25,
        "categoryId": "bc058798-d669-458b-8945-98bbe0ae4c4a",
        "locationId": "9859160a-5a33-4d71-a25b-b0d4e836805b"
    },
    {
        "name": "Cookbook",
        "description": "Healthy recipes cookbook",
        "price": 18.00,
        "quantity": 30,
        "categoryId": "2f70d404-8b93-461e-973d-b04152bf62aa",
        "locationId": "705be4d9-9bc8-4d7d-9d8e-817a512fab31"
    },
    {
        "name": "First Aid Kit",
        "description": "Comprehensive first aid kit",
        "price": 22.00,
        "quantity": 40,
        "categoryId": "b4a51cd7-1bf5-4607-ac70-bf97089d6f9c",
        "locationId": "ded85aaf-a776-4fb4-ae7a-01e7bd062d0b"
    }
]